[
 {
   "cefr": "",
   "def2": "",
   "def1": "много работы",
   "ipa": "ə lɑt ʌv wɜrk",
   "spell": "a lot of work"
 },
 {
   "cefr": "",
   "def2": "",
   "def1": "кондиционер",
   "ipa": "ən ɛr kənˈdɪʃənər",
   "spell": "an air conditioner"
 },
 {
   "cefr": "",
   "def2": "",
   "def1": "можете привести пример?",
   "ipa": "kæn ju ɡɪv mi ən ɪɡˈzæmpəl?",
   "spell": "can you give me an example?"
 },
 {
   "cefr": "",
   "def2": "",
   "def1": "у тебя сегодня есть работа?",
   "ipa": "du ju hæv wɜrk təˈdeɪ?",
   "spell": "do you have work today?"
 },
 {
   "cefr": "",
   "def2": "",
   "def1": "ты думаешь, мы сможем закончить сегодня?",
   "ipa": "du ju θɪŋk wi kæn ˈfɪnɪʃ təˈdeɪ?",
   "spell": "do you think we can finish today?"
 },
 {
   "cefr": "",
   "def2": "",
   "def1": "сколько градусов?",
   "ipa": "haʊ ˈmɛni dɪˈɡriz?",
   "spell": "how many degrees?"
 },
 {
   "cefr": "",
   "def2": "",
   "def1": "я выражаю то, что думаю",
   "ipa": "aɪ ɪkˈsprɛs wɑt aɪ θɪŋk",
   "spell": "I express what I think"
 },
 {
   "cefr": "",
   "def2": "",
   "def1": "мне нужно говорить",
   "ipa": "aɪ nid tu spik",
   "spell": "I need to speak"
 },
 {
   "cefr": "",
   "def2": "",
   "def1": "я говорю то, что думаю",
   "ipa": "aɪ seɪ wɑt aɪ θɪŋk",
   "spell": "I say what I think"
 },
 {
   "cefr": "",
   "def2": "",
   "def1": "я думаю",
   "ipa": "aɪ θɪŋk",
   "spell": "I think"
 },
 {
   "cefr": "",
   "def2": "",
   "def1": "давайте проверим",
   "ipa": "lɛt ʌs ˌriˈvju",
   "spell": "let us review"
 },
 {
   "cefr": "",
   "def2": "",
   "def1": "давайте попробуем",
   "ipa": "lɛts traɪ",
   "spell": "let's try"
 },
 {
   "cefr": "",
   "def2": "",
   "def1": "мои мысли",
   "ipa": "maɪ θɔts",
   "spell": "my thoughts"
 },
 {
   "cefr": "",
   "def2": "",
   "def1": "практика",
   "ipa": "ˈpræktəsɪŋ",
   "spell": "practicing"
 },
 {
   "cefr": "",
   "def2": "",
   "def1": "это приятно слышать",
   "ipa": "ðæt ɪz ɡʊd tu hir",
   "spell": "that is good to hear"
 },
 {
   "cefr": "",
   "def2": "",
   "def1": "голова боится, а рот говорит",
   "ipa": "ðə hɛd ɪz əˈfreɪd, bʌt ðə maʊθ spiks",
   "spell": "the head is afraid, but the mouth speaks"
 },
 {
   "cefr": "",
   "def2": "",
   "def1": "выражать",
   "ipa": "tu ɪkˈsprɛs",
   "spell": "to express"
 },
 {
   "cefr": "",
   "def2": "",
   "def1": "выражать свои мысли",
   "ipa": "tu ɪkˈsprɛs maɪ θɔts",
   "spell": "to express my thoughts"
 },
 {
   "cefr": "",
   "def2": "",
   "def1": "какое это слово?",
   "ipa": "wɪʧ wɜrd ɪz ɪt?",
   "spell": "which word is it?"
 },
 {
   "cefr": "",
   "def2": "",
   "def1": "ты думаешь, мы сможем закончить сегодня?",
   "ipa": "ju θɪŋk wi kæn ˈfɪnɪʃ təˈdeɪ?",
   "spell": "you think we can finish today?"
 }
]