[
 {
   "cefr": "",
   "def2": "",
   "def1": "кондуктор",
   "ipa": "ə bʌs kənˈdʌktər",
   "spell": "a bus conductor"
 },
 {
   "cefr": "",
   "def2": "",
   "def1": "дом культуры",
   "ipa": "ə kəmˈjunəti ˈsɛntər",
   "spell": "a community center"
 },
 {
   "cefr": "",
   "def2": "",
   "def1": "китаист, китаевед",
   "ipa": "ə saɪˈnɑlədʒɪst",
   "spell": "a sinologist"
 },
 {
   "cefr": "",
   "def2": "",
   "def1": "солнечная панель",
   "ipa": "ə ˈsoʊlər ˈpænəl",
   "spell": "a solar panel"
 },
 {
   "cefr": "",
   "def2": "",
   "def1": "знакомый",
   "ipa": "ən əˈkweɪntəns",
   "spell": "an acquaintance"
 },
 {
   "cefr": "",
   "def2": "",
   "def1": "открытый бассейн",
   "ipa": "ən ˈoʊpən-ɛr pul",
   "spell": "an open-air pool"
 },
 {
   "cefr": "",
   "def2": "",
   "def1": "очарованный",
   "ipa": "ˈfæsəˌneɪtɪd",
   "spell": "fascinated"
 },
 {
   "cefr": "",
   "def2": "",
   "def1": "бережливый",
   "ipa": "ˈfruɡəl",
   "spell": "frugal"
 },
 {
   "cefr": "",
   "def2": "",
   "def1": "бережливость",
   "ipa": "fruˈɡæləti",
   "spell": "frugality"
 },
 {
   "cefr": "",
   "def2": "",
   "def1": "жадный",
   "ipa": "ˈɡridi",
   "spell": "greedy"
 },
 {
   "cefr": "",
   "def2": "",
   "def1": "в итоге он отыграл со мной весь концерт",
   "ipa": "hi ˈɛndɪd ʌp ˈduɪŋ ðə hoʊl ˈkɑnsɜrt wɪð mi",
   "spell": "he ended up doing the whole concert with me"
 },
 {
   "cefr": "",
   "def2": "",
   "def1": "её подход к музыке",
   "ipa": "hɜr əˈproʊʧ tu ˈmjuzɪk",
   "spell": "her approach to music"
 },
 {
   "cefr": "",
   "def2": "",
   "def1": "я не стал",
   "ipa": "aɪ dɪd nɑt bɪˈkʌm",
   "spell": "I did not become"
 },
 {
   "cefr": "",
   "def2": "",
   "def1": "я должен сделать это до двадцати пяти лет",
   "ipa": "aɪ hæv tu du ðɪs bɪˈfɔr aɪm ˈtwɛnti faɪv",
   "spell": "I have to do this before I'm twenty five"
 },
 {
   "cefr": "",
   "def2": "",
   "def1": "я там родился и вырос",
   "ipa": "aɪ wʌz bɔrn ænd reɪzd ðɛr",
   "spell": "I was born and raised there"
 },
 {
   "cefr": "",
   "def2": "",
   "def1": "это было немного шокирующим",
   "ipa": "ɪt wʌz ə bɪt ˈʃɑkɪŋ",
   "spell": "it was a bit shocking"
 },
 {
   "cefr": "",
   "def2": "",
   "def1": "много людей",
   "ipa": "ˈmɛni ˈpipəl",
   "spell": "many people"
 },
 {
   "cefr": "",
   "def2": "",
   "def1": "так много целей",
   "ipa": "soʊ ˈmɛni ɡoʊlz",
   "spell": "so many goals"
 },
 {
   "cefr": "",
   "def2": "",
   "def1": "они беззаботны",
   "ipa": "ðeɪ ɑr ˈkɛrˌfri",
   "spell": "they are carefree"
 },
 {
   "cefr": "",
   "def2": "",
   "def1": "они сходят с ума",
   "ipa": "ðeɪ draɪv ðɛmˈsɛlvz ˈkreɪzi",
   "spell": "they drive themselves crazy"
 },
 {
   "cefr": "",
   "def2": "",
   "def1": "воспитывать её",
   "ipa": "tu brɪŋ hɜr ʌp",
   "spell": "to bring her up"
 },
 {
   "cefr": "",
   "def2": "",
   "def1": "искать выгодные предложения",
   "ipa": "tu lʊk fɔr dilz",
   "spell": "to look for deals"
 },
 {
   "cefr": "",
   "def2": "",
   "def1": "искать скидки",
   "ipa": "tu lʊk fɔr seɪlz",
   "spell": "to look for sales"
 },
 {
   "cefr": "",
   "def2": "",
   "def1": "воспитание",
   "ipa": "ˈʌpˌbrɪŋɪŋ",
   "spell": "upbringing"
 },
 {
   "cefr": "",
   "def2": "",
   "def1": "восстание",
   "ipa": "əˈpraɪzɪŋ",
   "spell": "uprising"
 },
 {
   "cefr": "",
   "def2": "",
   "def1": "нам не нужно тратить деньги",
   "ipa": "wi doʊnt hæv tu spɛnd ðə ˈmʌni",
   "spell": "we don't have to spend the money"
 }
]