[
    {
        "cefr": "",
        "def1": "сценарий",
        "ipa": "ə sɪˈnɛrioʊ",
        "spell": "a scenario"
    },
    {
        "cefr": "",
        "def1": "использование, применение",
        "ipa": "jus",
        "spell": "use"
    },
    {
        "cefr": "",
        "def1": "вставлять в гнездо",
        "ipa": "tu plʌɡ",
        "spell": "to plug"
    },
    {
        "cefr": "",
        "def1": "квартиросъёмщик",
        "ipa": "ə ˈrɛntər",
        "spell": "a renter"
    },
    {
        "cefr": "",
        "def1": "получатель",
        "ipa": "ə rəˈsɪpiənt",
        "spell": "a recipient"
    },
    {
        "cefr": "",
        "def1": "использовать, применять",
        "ipa": "tu juz",
        "spell": "to use"
    },
    {
        "cefr": "",
        "def1": "соединять, сливать",
        "ipa": "tu juˈnaɪt",
        "spell": "to unite"
    },
    {
        "cefr": "",
        "def1": "откуда угодно",
        "ipa": "frʌm ˈɛniˌwɛr",
        "spell": "from anywhere"
    },
    {
        "cefr": "",
        "def1": "порядок слов",
        "ipa": "ðə wɜrd ˈɔrdər",
        "spell": "the word order"
    },
    {
        "cefr": "",
        "def1": "если ...  тогда ...",
        "ipa": "ɪf … ðɛn ….",
        "spell": "if … then …."
    },
    {
        "cefr": "",
        "def1": "варианты (из разных категорий)",
        "ipa": "ˈɑpʃənz",
        "spell": "options"
    },
    {
        "cefr": "",
        "def1": "ветровое, лобовое стекло",
        "ipa": "ˈwɪndˌʃild",
        "spell": "windshield"
    },
    {
        "cefr": "",
        "def1": "варианты (из одной категории)",
        "ipa": "ˈvɛriənts",
        "spell": "variants"
    },
    {
        "cefr": "",
        "def1": "объединять, комбинировать",
        "ipa": "tu kəmˈbaɪn",
        "spell": "to combine"
    },
    {
        "cefr": "",
        "def1": "до начала рабочего дня",
        "ipa": "bɪˈfɔr ˈaʊərz",
        "spell": "before hours"
    },
    {
        "cefr": "",
        "def1": "закрыто и заперто",
        "ipa": "kloʊzd ænd lɑkt",
        "spell": "closed and locked"
    },
    {
        "cefr": "",
        "def1": "закрыть и запереть",
        "ipa": "tu kloʊs ænd lɑk",
        "spell": "to close and lock"
    },
    {
        "cefr": "",
        "def1": "на его почтовый ящик",
        "ipa": "tu hɪz meɪl bɑks",
        "spell": "to his mail box"
    },
    {
        "cefr": "",
        "def1": "отключить",
        "ipa": "tu swɪʧ ɔf, tɜrn ɔf",
        "spell": "to switch off, turn off"
    },
    {
        "cefr": "",
        "def1": "после окончания рабочего дня",
        "ipa": "ˈæftər ˈaʊərz",
        "spell": "after hours"
    },
    {
        "cefr": "",
        "def1": "незаперто и открыто",
        "ipa": "ənˈlɑkt ænd ˈoʊpən",
        "spell": "unlocked and open"
    },
    {
        "cefr": "",
        "def1": "в рабочее время",
        "ipa": "ˈdʊrɪŋ ˈwɜrkɪŋ ˈaʊərz",
        "spell": "during working hours"
    },
    {
        "cefr": "",
        "def1": "они программируются",
        "ipa": "ðeɪ ɑr ˈproʊˌɡræmd",
        "spell": "they are programmed"
    },
    {
        "cefr": "",
        "def1": "площадка (концертная, танцевальная и т.п.)",
        "ipa": "ə ˈvɛnju",
        "spell": "a venue"
    },
    {
        "cefr": "",
        "def1": "закрыто, но не заперто",
        "ipa": "kloʊzd bʌt ənˈlɑkt",
        "spell": "closed but unlocked"
    },
    {
        "cefr": "",
        "def1": "не закрывается совсем",
        "ipa": "ˈdʌzənt kloʊs æt ɔl",
        "spell": "doesn’t close at all"
    },
    {
        "cefr": "",
        "def1": "воровство в магазинах, магазинные кражи",
        "ipa": "ˈʃɑˌplɪftɪŋ",
        "spell": "shoplifting"
    },
    {
        "cefr": "",
        "def1": "неудобно для них",
        "ipa": "nɑt kənˈvinjənt fɔr ðɛm",
        "spell": "not convenient for them"
    },
    {
        "cefr": "",
        "def1": "в течение рабочего дня",
        "ipa": "ˈdʊrɪŋ ˈbɪznəs ˈaʊərz",
        "spell": "during business hours"
    },
    {
        "cefr": "",
        "def1": "попытка украсть это",
        "ipa": "ən əˈtɛmpt tu stil ðæt",
        "spell": "an attempt to steal that"
    },
    {
        "cefr": "",
        "def1": "позволить ему сделать это",
        "ipa": "tu əˈlaʊ hɪm tu du ðæt",
        "spell": "to allow him to do that"
    },
    {
        "cefr": "",
        "def1": "получатель электронной почты, адресат",
        "ipa": "ə meɪl rəˈsɪpiənt",
        "spell": "a mail recipient"
    },
    {
        "cefr": "",
        "def1": "ворота не смогли закрыться",
        "ipa": "ðə ɡeɪt feɪld tu kloʊs",
        "spell": "the gate failed to close"
    },
    {
        "cefr": "",
        "def1": "на их аварийных выходах",
        "ipa": "æt ðɛr ɪˈmɜrʤənsi ˈɛɡzɪts",
        "spell": "at their emergency exits"
    },
    {
        "cefr": "",
        "def1": "круглосуточный доступ",
        "ipa": "ə ˈtwɛnti-fɔr-ˈaʊər ˈækˌsɛs",
        "spell": "a twenty-four-hour access"
    },
    {
        "cefr": "",
        "def1": "не закрывается полностью",
        "ipa": "dʌz nɑt kloʊs kəmˈplitli",
        "spell": "does not close completely"
    },
    {
        "cefr": "",
        "def1": "представить уведомление",
        "ipa": "tu prəˈvaɪd ˌnoʊtəfəˈkeɪʃən",
        "spell": "to provide notification"
    },
    {
        "cefr": "",
        "def1": "в конкретные часы дня",
        "ipa": "æt spəˈsɪfɪk ˈaʊərz ʌv ðə deɪ",
        "spell": "at specific hours of the day"
    },
    {
        "cefr": "",
        "def1": "в отличие от наших конкурентов",
        "ipa": "ənˈlaɪk ˈaʊər kəmˈpɛtətərz",
        "spell": "unlike our competitors"
    },
    {
        "cefr": "",
        "def1": "каждый тип удостоверяющей информации",
        "ipa": "iʧ taɪp ʌv krɪˈdɛnʧəl",
        "spell": "each type of credential"
    },
    {
        "cefr": "",
        "def1": "человек получит что-то",
        "ipa": "ˈsʌmˌbɑdi wɪl rəˈsiv ˈsʌmθɪŋ",
        "spell": "somebody will receive something"
    },
    {
        "cefr": "",
        "def1": "это одно из ключевых преимуществ",
        "ipa": "ɪts wʌn ʌv ðə ki ædˈvæntɪʤɪz",
        "spell": "it’s one of the key advantages"
    },
    {
        "cefr": "",
        "def1": "регулятор функционирует нестабильно",
        "ipa": "ðɪs kənˈtroʊlər ɪz ənˈsteɪbəl",
        "spell": "this controller is unstable"
    },
    {
        "cefr": "",
        "def1": "это одно из наших главных преимуществ",
        "ipa": "ɪt ɪz wʌn ʌv ˈaʊər meɪn ˈbɛnəfɪts",
        "spell": "it is one of our main benefits"
    },
    {
        "cefr": "",
        "def1": "что-то будет получено человеком",
        "ipa": "ˈsʌmθɪŋ wɪl bi rəˈsivd baɪ ˈsʌmˌbɑdi",
        "spell": "something will be received by somebody"
    },
    {
        "cefr": "",
        "def1": "сделать так, чтобы система (сделала что-то)",
        "ipa": "tu hæv ðə ˈsɪstəm tu (du ˈsʌmθɪŋ)",
        "spell": "to have the system to (do something)"
    }
]